{
  "basics": {
    "name": "Jeffrey Suen",
    "label": "Student",
    "picture": "https://jeffsuen.github.io/images/headshot2.jpg",
    "email": "sj39@hawaii.edu",
    "phone": "",
    "website": "https://jeffsuen.github.io",
    "summary": "I am studying for a B.A. in Computer Science in the Department of Information and Computer Sciences at the University of Hawaii. I expect to graduate in Spring, 2020.",
    "location": {
      "address": "",
      "postalCode": "96822",
      "city": "Honolulu",
      "countryCode": "USA",
      "region": "Hawaii"
    },
    "profiles": [
      {
        "network": "github",
        "username": "jeffsuen",
        "url": "http://github.com/jeffsuen"
      },
      {
        "network": "linkedin",
        "username": "JeffreySuen",
        "url": "https://www.linkedin.com/in/jeffreysuen"
      },
    ]
  },
  "interests": [
    {
      "name": "Modern Media",
      "keywords": [
      ]
    },
    {
      "name": "Video Games",
      "keywords": [
      ]
    },
    {
      "name": "eSports",
      "keywords": [
      ]
    }
  ],
  "skills": [
    {
      "name": "Languages",
      "level": "",
      "keywords": [
        "C",
        "Java",
      ]
    },
    {
      "name": "Toolsets/Frameworks",
      "level": "",
      "keywords": [
        "Git/GitHub",
        "Unity Development Tool",
        "Semantic UI",
        "React",
      ]
    }
  ],
  "education": [
    {
      "institution": "University of Hawaii, Honolulu, HI",
      "area": "Computer Science (expected Spring, 2020)",
      "studyType": "B.A.",
      "startDate": "2017-05-07",
      "gpa": "",
      "courses": [
      ]
    }
  ],
  "work": [
    {
      "company": "UH Information Technology Services",
      "position": "Information Technology Student Assistant",
      "website": "http://www.hawaii.edu/its/",
      "startDate": "2017-07-10",
      "endDate": "Present",
      "summary": "",
      "highlights": [
        "Troubleshoot software, hardware and networking issues over the phone",
        "Answer phone and email responses to the ITS Help Desk"
      ]
    }
  ],
  "volunteer": [
    {
      "organization": "Kawananakoa Middle School Summer Program",
      "website": "",
      "position": "Assistant Music Teacher",
      "startDate": "2011-6-15",
      "endDate": "2017-7-15",
      "summary": "Instructed cello to novice-advanced instrumentalists",
      "highlights": [
        "Month long program to teach music to middle schoolers",
        "Taught basics to beginners and advanced techniques to returnees"
      ]
    },
    {
      "organization": "eSports Hawaii",
      "website": "",
      "position": "High School eSports Representative",
      "startDate": "2014-9-13",
      "endDate": "2015-5-26",
      "summary": "Communicated as a representative for the esports team at Roosevelt High School",
      "highlights": [
        "Managed relations and communications with multiple other high school representatives",
        "Was in charge of scheduling inter-high school matches",
      ]
    }
  ],
  "awards": [
    {
      "title": "Senior Honor Award",
      "date": "2014-2015",
      "awarder": "Roosevelt High School Music Department",
      "summary": "Given to notable music students whose ability and dedication enhanced the entire orchestra."
    },
  ],
  "references": [
    {
      "name": "Available upon request",
      "reference": ""
    }
  ]
}
